{
    "tracks": {
      "href": "https://api.spotify.com/v1/search?query=Road+to+the+Riches+Kool+G+Rap&type=track&offset=0&limit=5",
      "items": [
        {
          "album": {
            "album_type": "album",
            "artists": [
              {
                "external_urls": {
                  "spotify": "https://open.spotify.com/artist/099tLNCZZvtjC7myKD0mFp"
                },
                "href": "https://api.spotify.com/v1/artists/099tLNCZZvtjC7myKD0mFp",
                "id": "099tLNCZZvtjC7myKD0mFp",
                "name": "Kool G Rap",
                "type": "artist",
                "uri": "spotify:artist:099tLNCZZvtjC7myKD0mFp"
              },
              {
                "external_urls": {
                  "spotify": "https://open.spotify.com/artist/4WvLVxw1N375OetRwt2HRK"
                },
                "href": "https://api.spotify.com/v1/artists/4WvLVxw1N375OetRwt2HRK",
                "id": "4WvLVxw1N375OetRwt2HRK",
                "name": "DJ Polo",
                "type": "artist",
                "uri": "spotify:artist:4WvLVxw1N375OetRwt2HRK"
              }
            ],
            "available_markets": [
              "AD",
              "AE",
              "AL",
              "AR",
              "AT",
              "AU",
              "BA",
              "BE",
              "BG",
              "BH",
              "BO",
              "BR",
              "BY",
              "CA",
              "CH",
              "CL",
              "CO",
              "CR",
              "CY",
              "CZ",
              "DE",
              "DK",
              "DO",
              "DZ",
              "EC",
              "EE",
              "EG",
              "ES",
              "FI",
              "FR",
              "GB",
              "GR",
              "GT",
              "HK",
              "HN",
              "HR",
              "HU",
              "ID",
              "IE",
              "IL",
              "IN",
              "IS",
              "IT",
              "JO",
              "JP",
              "KW",
              "KZ",
              "LB",
              "LI",
              "LT",
              "LU",
              "LV",
              "MA",
              "MC",
              "MD",
              "MK",
              "MT",
              "MX",
              "MY",
              "NI",
              "NL",
              "NO",
              "NZ",
              "OM",
              "PA",
              "PE",
              "PH",
              "PL",
              "PT",
              "PY",
              "QA",
              "RO",
              "RS",
              "RU",
              "SA",
              "SE",
              "SG",
              "SI",
              "SK",
              "SV",
              "TH",
              "TN",
              "TR",
              "TW",
              "UA",
              "US",
              "UY",
              "VN",
              "XK",
              "ZA"
            ],
            "external_urls": {
              "spotify": "https://open.spotify.com/album/1J4VGPOpsMoIStSQGRpbh7"
            },
            "href": "https://api.spotify.com/v1/albums/1J4VGPOpsMoIStSQGRpbh7",
            "id": "1J4VGPOpsMoIStSQGRpbh7",
            "images": [
              {
                "height": 640,
                "url": "https://i.scdn.co/image/ab67616d0000b2732b95f111384ecd747de9a25f",
                "width": 640
              },
              {
                "height": 300,
                "url": "https://i.scdn.co/image/ab67616d00001e022b95f111384ecd747de9a25f",
                "width": 300
              },
              {
                "height": 64,
                "url": "https://i.scdn.co/image/ab67616d000048512b95f111384ecd747de9a25f",
                "width": 64
              }
            ],
            "name": "Road To The Riches",
            "release_date": "1989-03-14",
            "release_date_precision": "day",
            "total_tracks": 11,
            "type": "album",
            "uri": "spotify:album:1J4VGPOpsMoIStSQGRpbh7"
          },
          "artists": [
            {
              "external_urls": {
                "spotify": "https://open.spotify.com/artist/099tLNCZZvtjC7myKD0mFp"
              },
              "href": "https://api.spotify.com/v1/artists/099tLNCZZvtjC7myKD0mFp",
              "id": "099tLNCZZvtjC7myKD0mFp",
              "name": "Kool G Rap",
              "type": "artist",
              "uri": "spotify:artist:099tLNCZZvtjC7myKD0mFp"
            },
            {
              "external_urls": {
                "spotify": "https://open.spotify.com/artist/4WvLVxw1N375OetRwt2HRK"
              },
              "href": "https://api.spotify.com/v1/artists/4WvLVxw1N375OetRwt2HRK",
              "id": "4WvLVxw1N375OetRwt2HRK",
              "name": "DJ Polo",
              "type": "artist",
              "uri": "spotify:artist:4WvLVxw1N375OetRwt2HRK"
            }
          ],
          "available_markets": [
            "AD",
            "AE",
            "AL",
            "AR",
            "AT",
            "AU",
            "BA",
            "BE",
            "BG",
            "BH",
            "BO",
            "BR",
            "BY",
            "CA",
            "CH",
            "CL",
            "CO",
            "CR",
            "CY",
            "CZ",
            "DE",
            "DK",
            "DO",
            "DZ",
            "EC",
            "EE",
            "EG",
            "ES",
            "FI",
            "FR",
            "GB",
            "GR",
            "GT",
            "HK",
            "HN",
            "HR",
            "HU",
            "ID",
            "IE",
            "IL",
            "IN",
            "IS",
            "IT",
            "JO",
            "JP",
            "KW",
            "KZ",
            "LB",
            "LI",
            "LT",
            "LU",
            "LV",
            "MA",
            "MC",
            "MD",
            "MK",
            "MT",
            "MX",
            "MY",
            "NI",
            "NL",
            "NO",
            "NZ",
            "OM",
            "PA",
            "PE",
            "PH",
            "PL",
            "PT",
            "PY",
            "QA",
            "RO",
            "RS",
            "RU",
            "SA",
            "SE",
            "SG",
            "SI",
            "SK",
            "SV",
            "TH",
            "TN",
            "TR",
            "TW",
            "UA",
            "US",
            "UY",
            "VN",
            "XK",
            "ZA"
          ],
          "disc_number": 1,
          "duration_ms": 316866,
          "explicit": true,
          "external_ids": {
            "isrc": "CA5KR1969388"
          },
          "external_urls": {
            "spotify": "https://open.spotify.com/track/2V7BGxa9Bso5xoL1l7hitV"
          },
          "href": "https://api.spotify.com/v1/tracks/2V7BGxa9Bso5xoL1l7hitV",
          "id": "2V7BGxa9Bso5xoL1l7hitV",
          "is_local": false,
          "name": "Road To The Riches",
          "popularity": 37,
          "preview_url": "https://p.scdn.co/mp3-preview/25dab8dd9ced7d3a55b6ced5ceabb05de92001f9?cid=774b29d4f13844c495f206cafdad9c86",
          "track_number": 1,
          "type": "track",
          "uri": "spotify:track:2V7BGxa9Bso5xoL1l7hitV"
        },
        {
          "album": {
            "album_type": "album",
            "artists": [
              {
                "external_urls": {
                  "spotify": "https://open.spotify.com/artist/3P9vWhSo2PjRdxBvJutKIq"
                },
                "href": "https://api.spotify.com/v1/artists/3P9vWhSo2PjRdxBvJutKIq",
                "id": "3P9vWhSo2PjRdxBvJutKIq",
                "name": "Hush",
                "type": "artist",
                "uri": "spotify:artist:3P9vWhSo2PjRdxBvJutKIq"
              }
            ],
            "available_markets": [
              "AD",
              "AE",
              "AL",
              "AR",
              "AT",
              "AU",
              "BA",
              "BE",
              "BG",
              "BH",
              "BO",
              "BR",
              "CA",
              "CH",
              "CL",
              "CO",
              "CR",
              "CY",
              "CZ",
              "DE",
              "DK",
              "DO",
              "DZ",
              "EC",
              "EE",
              "EG",
              "ES",
              "FI",
              "FR",
              "GB",
              "GR",
              "GT",
              "HK",
              "HN",
              "HR",
              "HU",
              "ID",
              "IE",
              "IL",
              "IN",
              "IS",
              "IT",
              "JO",
              "JP",
              "KW",
              "KZ",
              "LB",
              "LI",
              "LT",
              "LU",
              "LV",
              "MA",
              "MC",
              "MD",
              "ME",
              "MK",
              "MT",
              "MX",
              "MY",
              "NI",
              "NL",
              "NO",
              "NZ",
              "OM",
              "PA",
              "PE",
              "PH",
              "PL",
              "PS",
              "PT",
              "PY",
              "QA",
              "RO",
              "RU",
              "SA",
              "SE",
              "SG",
              "SI",
              "SK",
              "SV",
              "TH",
              "TN",
              "TR",
              "TW",
              "UA",
              "US",
              "UY",
              "VN",
              "ZA"
            ],
            "external_urls": {
              "spotify": "https://open.spotify.com/album/50c9LilHsSbetnSfpzNa07"
            },
            "href": "https://api.spotify.com/v1/albums/50c9LilHsSbetnSfpzNa07",
            "id": "50c9LilHsSbetnSfpzNa07",
            "images": [
              {
                "height": 640,
                "url": "https://i.scdn.co/image/ab67616d0000b273dfc5a2d399275f876eec9cfc",
                "width": 640
              },
              {
                "height": 300,
                "url": "https://i.scdn.co/image/ab67616d00001e02dfc5a2d399275f876eec9cfc",
                "width": 300
              },
              {
                "height": 64,
                "url": "https://i.scdn.co/image/ab67616d00004851dfc5a2d399275f876eec9cfc",
                "width": 64
              }
            ],
            "name": "Bulletproof",
            "release_date": "2018-06-08",
            "release_date_precision": "day",
            "total_tracks": 12,
            "type": "album",
            "uri": "spotify:album:50c9LilHsSbetnSfpzNa07"
          },
          "artists": [
            {
              "external_urls": {
                "spotify": "https://open.spotify.com/artist/3P9vWhSo2PjRdxBvJutKIq"
              },
              "href": "https://api.spotify.com/v1/artists/3P9vWhSo2PjRdxBvJutKIq",
              "id": "3P9vWhSo2PjRdxBvJutKIq",
              "name": "Hush",
              "type": "artist",
              "uri": "spotify:artist:3P9vWhSo2PjRdxBvJutKIq"
            }
          ],
          "available_markets": [
            "AD",
            "AE",
            "AL",
            "AR",
            "AT",
            "AU",
            "BA",
            "BE",
            "BG",
            "BH",
            "BO",
            "BR",
            "CA",
            "CH",
            "CL",
            "CO",
            "CR",
            "CY",
            "CZ",
            "DE",
            "DK",
            "DO",
            "DZ",
            "EC",
            "EE",
            "EG",
            "ES",
            "FI",
            "FR",
            "GB",
            "GR",
            "GT",
            "HK",
            "HN",
            "HR",
            "HU",
            "ID",
            "IE",
            "IL",
            "IN",
            "IS",
            "IT",
            "JO",
            "JP",
            "KW",
            "KZ",
            "LB",
            "LI",
            "LT",
            "LU",
            "LV",
            "MA",
            "MC",
            "MD",
            "ME",
            "MK",
            "MT",
            "MX",
            "MY",
            "NI",
            "NL",
            "NO",
            "NZ",
            "OM",
            "PA",
            "PE",
            "PH",
            "PL",
            "PS",
            "PT",
            "PY",
            "QA",
            "RO",
            "RU",
            "SA",
            "SE",
            "SG",
            "SI",
            "SK",
            "SV",
            "TH",
            "TN",
            "TR",
            "TW",
            "UA",
            "US",
            "UY",
            "VN",
            "ZA"
          ],
          "disc_number": 1,
          "duration_ms": 237426,
          "explicit": true,
          "external_ids": {
            "isrc": "QMD9X1300037"
          },
          "external_urls": {
            "spotify": "https://open.spotify.com/track/4S0claVHzVyQiDNRs66CNs"
          },
          "href": "https://api.spotify.com/v1/tracks/4S0claVHzVyQiDNRs66CNs",
          "id": "4S0claVHzVyQiDNRs66CNs",
          "is_local": false,
          "name": "Superstar",
          "popularity": 10,
          "preview_url": "https://p.scdn.co/mp3-preview/0c270fb0dfdfbf5cf8d766f4b620885242e06c37?cid=774b29d4f13844c495f206cafdad9c86",
          "track_number": 9,
          "type": "track",
          "uri": "spotify:track:4S0claVHzVyQiDNRs66CNs"
        },
        {
          "album": {
            "album_type": "album",
            "artists": [
              {
                "external_urls": {
                  "spotify": "https://open.spotify.com/artist/099tLNCZZvtjC7myKD0mFp"
                },
                "href": "https://api.spotify.com/v1/artists/099tLNCZZvtjC7myKD0mFp",
                "id": "099tLNCZZvtjC7myKD0mFp",
                "name": "Kool G Rap",
                "type": "artist",
                "uri": "spotify:artist:099tLNCZZvtjC7myKD0mFp"
              },
              {
                "external_urls": {
                  "spotify": "https://open.spotify.com/artist/4WvLVxw1N375OetRwt2HRK"
                },
                "href": "https://api.spotify.com/v1/artists/4WvLVxw1N375OetRwt2HRK",
                "id": "4WvLVxw1N375OetRwt2HRK",
                "name": "DJ Polo",
                "type": "artist",
                "uri": "spotify:artist:4WvLVxw1N375OetRwt2HRK"
              }
            ],
            "available_markets": [
              "AD",
              "AE",
              "AL",
              "AR",
              "AT",
              "AU",
              "BA",
              "BE",
              "BG",
              "BH",
              "BO",
              "BR",
              "BY",
              "CA",
              "CH",
              "CL",
              "CO",
              "CR",
              "CY",
              "CZ",
              "DE",
              "DK",
              "DO",
              "DZ",
              "EC",
              "EE",
              "EG",
              "ES",
              "FI",
              "FR",
              "GB",
              "GR",
              "GT",
              "HK",
              "HN",
              "HR",
              "HU",
              "ID",
              "IE",
              "IL",
              "IN",
              "IS",
              "IT",
              "JO",
              "JP",
              "KW",
              "KZ",
              "LB",
              "LI",
              "LT",
              "LU",
              "LV",
              "MA",
              "MC",
              "MD",
              "MK",
              "MT",
              "MX",
              "MY",
              "NI",
              "NL",
              "NO",
              "NZ",
              "OM",
              "PA",
              "PE",
              "PH",
              "PL",
              "PT",
              "PY",
              "QA",
              "RO",
              "RS",
              "RU",
              "SA",
              "SE",
              "SG",
              "SI",
              "SK",
              "SV",
              "TH",
              "TN",
              "TR",
              "TW",
              "UA",
              "US",
              "UY",
              "VN",
              "XK",
              "ZA"
            ],
            "external_urls": {
              "spotify": "https://open.spotify.com/album/1J4VGPOpsMoIStSQGRpbh7"
            },
            "href": "https://api.spotify.com/v1/albums/1J4VGPOpsMoIStSQGRpbh7",
            "id": "1J4VGPOpsMoIStSQGRpbh7",
            "images": [
              {
                "height": 640,
                "url": "https://i.scdn.co/image/ab67616d0000b2732b95f111384ecd747de9a25f",
                "width": 640
              },
              {
                "height": 300,
                "url": "https://i.scdn.co/image/ab67616d00001e022b95f111384ecd747de9a25f",
                "width": 300
              },
              {
                "height": 64,
                "url": "https://i.scdn.co/image/ab67616d000048512b95f111384ecd747de9a25f",
                "width": 64
              }
            ],
            "name": "Road To The Riches",
            "release_date": "1989-03-14",
            "release_date_precision": "day",
            "total_tracks": 11,
            "type": "album",
            "uri": "spotify:album:1J4VGPOpsMoIStSQGRpbh7"
          },
          "artists": [
            {
              "external_urls": {
                "spotify": "https://open.spotify.com/artist/099tLNCZZvtjC7myKD0mFp"
              },
              "href": "https://api.spotify.com/v1/artists/099tLNCZZvtjC7myKD0mFp",
              "id": "099tLNCZZvtjC7myKD0mFp",
              "name": "Kool G Rap",
              "type": "artist",
              "uri": "spotify:artist:099tLNCZZvtjC7myKD0mFp"
            },
            {
              "external_urls": {
                "spotify": "https://open.spotify.com/artist/4WvLVxw1N375OetRwt2HRK"
              },
              "href": "https://api.spotify.com/v1/artists/4WvLVxw1N375OetRwt2HRK",
              "id": "4WvLVxw1N375OetRwt2HRK",
              "name": "DJ Polo",
              "type": "artist",
              "uri": "spotify:artist:4WvLVxw1N375OetRwt2HRK"
            }
          ],
          "available_markets": [
            "AD",
            "AE",
            "AL",
            "AR",
            "AT",
            "AU",
            "BA",
            "BE",
            "BG",
            "BH",
            "BO",
            "BR",
            "BY",
            "CA",
            "CH",
            "CL",
            "CO",
            "CR",
            "CY",
            "CZ",
            "DE",
            "DK",
            "DO",
            "DZ",
            "EC",
            "EE",
            "EG",
            "ES",
            "FI",
            "FR",
            "GB",
            "GR",
            "GT",
            "HK",
            "HN",
            "HR",
            "HU",
            "ID",
            "IE",
            "IL",
            "IN",
            "IS",
            "IT",
            "JO",
            "JP",
            "KW",
            "KZ",
            "LB",
            "LI",
            "LT",
            "LU",
            "LV",
            "MA",
            "MC",
            "MD",
            "MK",
            "MT",
            "MX",
            "MY",
            "NI",
            "NL",
            "NO",
            "NZ",
            "OM",
            "PA",
            "PE",
            "PH",
            "PL",
            "PT",
            "PY",
            "QA",
            "RO",
            "RS",
            "RU",
            "SA",
            "SE",
            "SG",
            "SI",
            "SK",
            "SV",
            "TH",
            "TN",
            "TR",
            "TW",
            "UA",
            "US",
            "UY",
            "VN",
            "XK",
            "ZA"
          ],
          "disc_number": 1,
          "duration_ms": 269426,
          "explicit": true,
          "external_ids": {
            "isrc": "CA5KR1969389"
          },
          "external_urls": {
            "spotify": "https://open.spotify.com/track/6U1V6svVpMTa9v7tJ16K13"
          },
          "href": "https://api.spotify.com/v1/tracks/6U1V6svVpMTa9v7tJ16K13",
          "id": "6U1V6svVpMTa9v7tJ16K13",
          "is_local": false,
          "name": "It's A Demo",
          "popularity": 19,
          "preview_url": "https://p.scdn.co/mp3-preview/dece433aaefb2fd17b2d8ab426cd0f281350f3df?cid=774b29d4f13844c495f206cafdad9c86",
          "track_number": 2,
          "type": "track",
          "uri": "spotify:track:6U1V6svVpMTa9v7tJ16K13"
        },
        {
          "album": {
            "album_type": "album",
            "artists": [
              {
                "external_urls": {
                  "spotify": "https://open.spotify.com/artist/099tLNCZZvtjC7myKD0mFp"
                },
                "href": "https://api.spotify.com/v1/artists/099tLNCZZvtjC7myKD0mFp",
                "id": "099tLNCZZvtjC7myKD0mFp",
                "name": "Kool G Rap",
                "type": "artist",
                "uri": "spotify:artist:099tLNCZZvtjC7myKD0mFp"
              },
              {
                "external_urls": {
                  "spotify": "https://open.spotify.com/artist/4WvLVxw1N375OetRwt2HRK"
                },
                "href": "https://api.spotify.com/v1/artists/4WvLVxw1N375OetRwt2HRK",
                "id": "4WvLVxw1N375OetRwt2HRK",
                "name": "DJ Polo",
                "type": "artist",
                "uri": "spotify:artist:4WvLVxw1N375OetRwt2HRK"
              }
            ],
            "available_markets": [
              "AD",
              "AE",
              "AL",
              "AR",
              "AT",
              "AU",
              "BA",
              "BE",
              "BG",
              "BH",
              "BO",
              "BR",
              "BY",
              "CA",
              "CH",
              "CL",
              "CO",
              "CR",
              "CY",
              "CZ",
              "DE",
              "DK",
              "DO",
              "DZ",
              "EC",
              "EE",
              "EG",
              "ES",
              "FI",
              "FR",
              "GB",
              "GR",
              "GT",
              "HK",
              "HN",
              "HR",
              "HU",
              "ID",
              "IE",
              "IL",
              "IN",
              "IS",
              "IT",
              "JO",
              "JP",
              "KW",
              "KZ",
              "LB",
              "LI",
              "LT",
              "LU",
              "LV",
              "MA",
              "MC",
              "MD",
              "MK",
              "MT",
              "MX",
              "MY",
              "NI",
              "NL",
              "NO",
              "NZ",
              "OM",
              "PA",
              "PE",
              "PH",
              "PL",
              "PT",
              "PY",
              "QA",
              "RO",
              "RS",
              "RU",
              "SA",
              "SE",
              "SG",
              "SI",
              "SK",
              "SV",
              "TH",
              "TN",
              "TR",
              "TW",
              "UA",
              "US",
              "UY",
              "VN",
              "XK",
              "ZA"
            ],
            "external_urls": {
              "spotify": "https://open.spotify.com/album/1J4VGPOpsMoIStSQGRpbh7"
            },
            "href": "https://api.spotify.com/v1/albums/1J4VGPOpsMoIStSQGRpbh7",
            "id": "1J4VGPOpsMoIStSQGRpbh7",
            "images": [
              {
                "height": 640,
                "url": "https://i.scdn.co/image/ab67616d0000b2732b95f111384ecd747de9a25f",
                "width": 640
              },
              {
                "height": 300,
                "url": "https://i.scdn.co/image/ab67616d00001e022b95f111384ecd747de9a25f",
                "width": 300
              },
              {
                "height": 64,
                "url": "https://i.scdn.co/image/ab67616d000048512b95f111384ecd747de9a25f",
                "width": 64
              }
            ],
            "name": "Road To The Riches",
            "release_date": "1989-03-14",
            "release_date_precision": "day",
            "total_tracks": 11,
            "type": "album",
            "uri": "spotify:album:1J4VGPOpsMoIStSQGRpbh7"
          },
          "artists": [
            {
              "external_urls": {
                "spotify": "https://open.spotify.com/artist/099tLNCZZvtjC7myKD0mFp"
              },
              "href": "https://api.spotify.com/v1/artists/099tLNCZZvtjC7myKD0mFp",
              "id": "099tLNCZZvtjC7myKD0mFp",
              "name": "Kool G Rap",
              "type": "artist",
              "uri": "spotify:artist:099tLNCZZvtjC7myKD0mFp"
            },
            {
              "external_urls": {
                "spotify": "https://open.spotify.com/artist/4WvLVxw1N375OetRwt2HRK"
              },
              "href": "https://api.spotify.com/v1/artists/4WvLVxw1N375OetRwt2HRK",
              "id": "4WvLVxw1N375OetRwt2HRK",
              "name": "DJ Polo",
              "type": "artist",
              "uri": "spotify:artist:4WvLVxw1N375OetRwt2HRK"
            }
          ],
          "available_markets": [
            "AD",
            "AE",
            "AL",
            "AR",
            "AT",
            "AU",
            "BA",
            "BE",
            "BG",
            "BH",
            "BO",
            "BR",
            "BY",
            "CA",
            "CH",
            "CL",
            "CO",
            "CR",
            "CY",
            "CZ",
            "DE",
            "DK",
            "DO",
            "DZ",
            "EC",
            "EE",
            "EG",
            "ES",
            "FI",
            "FR",
            "GB",
            "GR",
            "GT",
            "HK",
            "HN",
            "HR",
            "HU",
            "ID",
            "IE",
            "IL",
            "IN",
            "IS",
            "IT",
            "JO",
            "JP",
            "KW",
            "KZ",
            "LB",
            "LI",
            "LT",
            "LU",
            "LV",
            "MA",
            "MC",
            "MD",
            "MK",
            "MT",
            "MX",
            "MY",
            "NI",
            "NL",
            "NO",
            "NZ",
            "OM",
            "PA",
            "PE",
            "PH",
            "PL",
            "PT",
            "PY",
            "QA",
            "RO",
            "RS",
            "RU",
            "SA",
            "SE",
            "SG",
            "SI",
            "SK",
            "SV",
            "TH",
            "TN",
            "TR",
            "TW",
            "UA",
            "US",
            "UY",
            "VN",
            "XK",
            "ZA"
          ],
          "disc_number": 1,
          "duration_ms": 312413,
          "explicit": true,
          "external_ids": {
            "isrc": "CA5KR1969391"
          },
          "external_urls": {
            "spotify": "https://open.spotify.com/track/2hyWfH4sUEJBqRoPzstl1O"
          },
          "href": "https://api.spotify.com/v1/tracks/2hyWfH4sUEJBqRoPzstl1O",
          "id": "2hyWfH4sUEJBqRoPzstl1O",
          "is_local": false,
          "name": "Truly Yours",
          "popularity": 15,
          "preview_url": "https://p.scdn.co/mp3-preview/2b8cb43c0fae78075108c0b91fbea8a803fd1fd5?cid=774b29d4f13844c495f206cafdad9c86",
          "track_number": 4,
          "type": "track",
          "uri": "spotify:track:2hyWfH4sUEJBqRoPzstl1O"
        },
        {
          "album": {
            "album_type": "album",
            "artists": [
              {
                "external_urls": {
                  "spotify": "https://open.spotify.com/artist/099tLNCZZvtjC7myKD0mFp"
                },
                "href": "https://api.spotify.com/v1/artists/099tLNCZZvtjC7myKD0mFp",
                "id": "099tLNCZZvtjC7myKD0mFp",
                "name": "Kool G Rap",
                "type": "artist",
                "uri": "spotify:artist:099tLNCZZvtjC7myKD0mFp"
              },
              {
                "external_urls": {
                  "spotify": "https://open.spotify.com/artist/4WvLVxw1N375OetRwt2HRK"
                },
                "href": "https://api.spotify.com/v1/artists/4WvLVxw1N375OetRwt2HRK",
                "id": "4WvLVxw1N375OetRwt2HRK",
                "name": "DJ Polo",
                "type": "artist",
                "uri": "spotify:artist:4WvLVxw1N375OetRwt2HRK"
              }
            ],
            "available_markets": [
              "AD",
              "AE",
              "AL",
              "AR",
              "AT",
              "AU",
              "BA",
              "BE",
              "BG",
              "BH",
              "BO",
              "BR",
              "BY",
              "CA",
              "CH",
              "CL",
              "CO",
              "CR",
              "CY",
              "CZ",
              "DE",
              "DK",
              "DO",
              "DZ",
              "EC",
              "EE",
              "EG",
              "ES",
              "FI",
              "FR",
              "GB",
              "GR",
              "GT",
              "HK",
              "HN",
              "HR",
              "HU",
              "ID",
              "IE",
              "IL",
              "IN",
              "IS",
              "IT",
              "JO",
              "JP",
              "KW",
              "KZ",
              "LB",
              "LI",
              "LT",
              "LU",
              "LV",
              "MA",
              "MC",
              "MD",
              "MK",
              "MT",
              "MX",
              "MY",
              "NI",
              "NL",
              "NO",
              "NZ",
              "OM",
              "PA",
              "PE",
              "PH",
              "PL",
              "PT",
              "PY",
              "QA",
              "RO",
              "RS",
              "RU",
              "SA",
              "SE",
              "SG",
              "SI",
              "SK",
              "SV",
              "TH",
              "TN",
              "TR",
              "TW",
              "UA",
              "US",
              "UY",
              "VN",
              "XK",
              "ZA"
            ],
            "external_urls": {
              "spotify": "https://open.spotify.com/album/1J4VGPOpsMoIStSQGRpbh7"
            },
            "href": "https://api.spotify.com/v1/albums/1J4VGPOpsMoIStSQGRpbh7",
            "id": "1J4VGPOpsMoIStSQGRpbh7",
            "images": [
              {
                "height": 640,
                "url": "https://i.scdn.co/image/ab67616d0000b2732b95f111384ecd747de9a25f",
                "width": 640
              },
              {
                "height": 300,
                "url": "https://i.scdn.co/image/ab67616d00001e022b95f111384ecd747de9a25f",
                "width": 300
              },
              {
                "height": 64,
                "url": "https://i.scdn.co/image/ab67616d000048512b95f111384ecd747de9a25f",
                "width": 64
              }
            ],
            "name": "Road To The Riches",
            "release_date": "1989-03-14",
            "release_date_precision": "day",
            "total_tracks": 11,
            "type": "album",
            "uri": "spotify:album:1J4VGPOpsMoIStSQGRpbh7"
          },
          "artists": [
            {
              "external_urls": {
                "spotify": "https://open.spotify.com/artist/099tLNCZZvtjC7myKD0mFp"
              },
              "href": "https://api.spotify.com/v1/artists/099tLNCZZvtjC7myKD0mFp",
              "id": "099tLNCZZvtjC7myKD0mFp",
              "name": "Kool G Rap",
              "type": "artist",
              "uri": "spotify:artist:099tLNCZZvtjC7myKD0mFp"
            },
            {
              "external_urls": {
                "spotify": "https://open.spotify.com/artist/4WvLVxw1N375OetRwt2HRK"
              },
              "href": "https://api.spotify.com/v1/artists/4WvLVxw1N375OetRwt2HRK",
              "id": "4WvLVxw1N375OetRwt2HRK",
              "name": "DJ Polo",
              "type": "artist",
              "uri": "spotify:artist:4WvLVxw1N375OetRwt2HRK"
            }
          ],
          "available_markets": [
            "AD",
            "AE",
            "AL",
            "AR",
            "AT",
            "AU",
            "BA",
            "BE",
            "BG",
            "BH",
            "BO",
            "BR",
            "BY",
            "CA",
            "CH",
            "CL",
            "CO",
            "CR",
            "CY",
            "CZ",
            "DE",
            "DK",
            "DO",
            "DZ",
            "EC",
            "EE",
            "EG",
            "ES",
            "FI",
            "FR",
            "GB",
            "GR",
            "GT",
            "HK",
            "HN",
            "HR",
            "HU",
            "ID",
            "IE",
            "IL",
            "IN",
            "IS",
            "IT",
            "JO",
            "JP",
            "KW",
            "KZ",
            "LB",
            "LI",
            "LT",
            "LU",
            "LV",
            "MA",
            "MC",
            "MD",
            "MK",
            "MT",
            "MX",
            "MY",
            "NI",
            "NL",
            "NO",
            "NZ",
            "OM",
            "PA",
            "PE",
            "PH",
            "PL",
            "PT",
            "PY",
            "QA",
            "RO",
            "RS",
            "RU",
            "SA",
            "SE",
            "SG",
            "SI",
            "SK",
            "SV",
            "TH",
            "TN",
            "TR",
            "TW",
            "UA",
            "US",
            "UY",
            "VN",
            "XK",
            "ZA"
          ],
          "disc_number": 1,
          "duration_ms": 323866,
          "explicit": true,
          "external_ids": {
            "isrc": "CA5KR1969394"
          },
          "external_urls": {
            "spotify": "https://open.spotify.com/track/0DDWeKK9lGDuoLXmHSqOBq"
          },
          "href": "https://api.spotify.com/v1/tracks/0DDWeKK9lGDuoLXmHSqOBq",
          "id": "0DDWeKK9lGDuoLXmHSqOBq",
          "is_local": false,
          "name": "She Loves Me, She Loves Me Not",
          "popularity": 11,
          "preview_url": "https://p.scdn.co/mp3-preview/b6f12cced8c0820a9dc21547a56080e849147b15?cid=774b29d4f13844c495f206cafdad9c86",
          "track_number": 7,
          "type": "track",
          "uri": "spotify:track:0DDWeKK9lGDuoLXmHSqOBq"
        }
      ],
      "limit": 5,
      "next": "https://api.spotify.com/v1/search?query=Road+to+the+Riches+Kool+G+Rap&type=track&offset=5&limit=5",
      "offset": 0,
      "previous": null,
      "total": 12
    }
  }